{
  "project_info": {
    "project_number": "453736336853",
    "project_id": "puvlic",
    "storage_bucket": "puvlic.appspot.com"
  },
  "client": [
    {
      "client_info": {
        "mobilesdk_app_id": "1:453736336853:android:23ba4cda8940b9b81fc15c",
        "android_client_info": {
          "package_name": "com.locator.besheger.locator"
        }
      },
      "oauth_client": [
        {
          "client_id": "453736336853-2ehopbs37ae4vo3qpshtdq2md8p2pno2.apps.googleusercontent.com",
          "client_type": 3
        }
      ],
      "api_key": [
        {
          "current_key": "AIzaSyAVfruC4sfFFXyWysSPlq7IMfpQ0gQQnow"
        }
      ],
      "services": {
        "appinvite_service": {
          "other_platform_oauth_client": [
            {
              "client_id": "453736336853-2ehopbs37ae4vo3qpshtdq2md8p2pno2.apps.googleusercontent.com",
              "client_type": 3
            },
            {
              "client_id": "453736336853-nb6rkk9slp27mc72ks9eh7f7vemq4t4i.apps.googleusercontent.com",
              "client_type": 2,
              "ios_info": {
                "bundle_id": "com.locator.besheger.locator"
              }
            }
          ]
        }
      }
    }
  ],
  "configuration_version": "1"
}